backup_docker_to_local-1.5.0.dist-info/licenses/LICENSE
baudolo/__init__.py
baudolo/backup/__init__.py
baudolo/backup/__main__.py
baudolo/backup/app.py
baudolo/backup/cli.py
baudolo/backup/compose.py
baudolo/backup/db.py
baudolo/backup/docker.py
baudolo/backup/shell.py
baudolo/backup/volume.py
baudolo/restore/__init__.py
baudolo/restore/__main__.py
baudolo/restore/files.py
baudolo/restore/paths.py
baudolo/restore/run.py
baudolo/restore/db/__init__.py
baudolo/restore/db/mariadb.py
baudolo/restore/db/postgres.py
baudolo/seed/__main__.py
backup_docker_to_local-1.5.0.dist-info/METADATA
backup_docker_to_local-1.5.0.dist-info/WHEEL
backup_docker_to_local-1.5.0.dist-info/entry_points.txt
backup_docker_to_local-1.5.0.dist-info/top_level.txt
backup_docker_to_local-1.5.0.dist-info/RECORD
