Metadata-Version: 2.4
Name: backup-docker-to-local
Version: 1.5.0
Summary: Backup Docker volumes to local with rsync and optional DB dumps.
Author: Kevin Veen-Birkenbach
License: AGPL-3.0-or-later
Requires-Python: >=3.9
License-File: LICENSE
Requires-Dist: pandas
Requires-Dist: dirval
Dynamic: license-file
